{
  "87aa121c-efbd-451a-8451-b3bdd6ce10b9": {
    "name": "丰富打斗细节的提示词",
    "category": "导入提示词",
    "content": "# AI小说创作：填充打斗细节的提示词\n\n本文档提供一系列提示词，旨在帮助AI在小说创作过程中，通过特定的打斗公式，更生动地填充打斗场景的细节。\n\n## 一、核心打斗公式：\n\n请围绕以下五个核心要素，细致描绘角色的每一次出手：\n\n1.  **神态与心理动作描写：** 角色在出招前、出招时、出招后的神态变化，以及内心活动（如决绝、犹豫、愤怒、冷静等）。\n2.  **出手时的音效：** 描述招式发动时产生的声音，例如破空声、金属碰撞声、能量爆鸣声、衣袂撕裂声等。\n3.  **出手造成的攻击特效：** 描述招式本身产生的视觉效果，例如剑光、拳风、法术光芒、气浪等。\n4.  **对手眼中，出手造成的攻击特效：** 从对手的视角描述攻击的威势和视觉冲击，强调其感受到的压迫感或惊异。\n5.  **出手造成的伤害描述：** 描述招式命中目标后造成的具体伤害效果，例如伤口情况、对手的反应（痛哼、后退、倒地等）、环境破坏等。\n\n## 二、具体应用提示\n\n### 提示词结构模板：\n\n“请为角色「[角色名A]」设计一个攻击动作，目标是「[角色名B/物体]」。\n\n1.  **神态与心理：** 在「[角色名A]」[准备/发动/完成]攻击时，其神态是「[具体神态，如：眼神冰冷、嘴角勾起一抹残忍的笑意、面色凝重]」，内心「[具体心理活动，如：充满了杀意、在计算最佳攻击时机、感到一丝不安但仍旧出手]」。\n2.  **音效：** 当「[角色名A]」的「[招式名/攻击方式，如：铁拳、长剑、法术]」出手时，发出了「[具体音效，如：沉闷的破风声、尖锐的剑鸣、能量汇聚的嗡鸣]」。\n3.  **攻击特效（自身视角）：** 「[角色名A]」的「[招式名/攻击方式]」在空中划出「[具体轨迹/形态，如：一道耀眼的白光、一团燃烧的火焰、无数细密的风刃]」，携带着「[具体气势，如：雷霆万钧之力、撕裂一切的锋锐、冰冷刺骨的寒意]」。\n4.  **攻击特效（对手视角）：** 在「[角色名B]」的眼中，「[角色名A]」的攻击如同「[具体比喻，如：一道不可抵挡的洪流、死神的镰刀、从天而降的审判之光]」，让他/她感到「[具体感受，如：窒息般的压迫、毛骨悚然的恐惧、无处可逃的绝望]」。\n5.  **伤害描述：** 「[招式名/攻击方式]」[击中/擦过/被格挡]「[角色名B]」的「[具体部位/武器]」后，「[角色名B]」[具体反应，如：闷哼一声，嘴角溢出鲜血、踉跄后退数步、兵器上出现裂痕、被击飞出去]，其「[受伤部位的具体描述，如：胸口出现一道深可见骨的伤痕、手臂被震得发麻、护体罡气瞬间破碎]」。同时，[周围环境可能发生的变化，如：地面龟裂、气浪吹飞了附近的杂物]。\n\n请基于此模板，详细描写该攻击场景。”\n\n### 示例：\n\n“请为角色「剑客李青」设计一个攻击动作，目标是「魔教长老」。\n\n1.  **神态与心理：** 在「剑客李青」发动攻击时，其神态是「眼神锐利如鹰隼，表情冷峻」，内心「充满了对邪魔外道的憎恶与必杀的决心」。\n2.  **音效：** 当「剑客李青」的「青锋剑」出手时，发出了「一声清越的龙吟般的剑鸣，以及剑锋高速切割空气产生的‘咻咻’声」。\n3.  **攻击特效（自身视角）：** 「剑客李青」的「青锋剑」在空中划出「一道迅疾如闪电的青色剑芒」，携带着「无匹的锋锐之气，仿佛能斩断世间一切」。\n4.  **攻击特效（对手视角）：** 在「魔教长老」的眼中，「剑客李青」的攻击如同「一道从九天之上降下的青色雷霆」，让他感到「一股死亡的阴影笼罩心头，避无可避」。\n5.  **伤害描述：** 「青锋剑」的剑芒掠过「魔教长老」的「左肩」后，「魔教长老」惨叫一声，左臂瞬间被齐肩斩断，鲜血如喷泉般涌出，他踉跄后退，脸上充满了难以置信的惊恐。同时，他身后的石壁被逸散的剑气划出数道深深的剑痕。\n\n请基于此模板，详细描写该攻击场景。”\n\n## 三、连续打斗与情境定制\n\n*   **指令：** “在接下来的[场景描述，如：狭窄的巷道中/华丽的宫殿内/广阔的草原上]，「[勇武]」与「[墨衡]」展开激烈搏杀。请运用上述五要素打斗公式，为他们设计至少三轮攻防转换，并注意通过神态、心理、音效、特效和伤害描述的递进，展现战斗的激烈程度和双方状态的变化。”\n*   **指令：** “针对以下人物设定：[角色A小传，包含武功特点和性格] 和 [角色B小传，包含武功特点和性格]，以及当前情境：[情境描述，如：突袭、遭遇战、生死决斗]。请创作一段他们之间的打斗场面，要求不仅要打斗激烈，还要通过打斗细节鲜明地展现其性格特点和武功路数。”\n\n希望这些提示词能帮助AI创作出更加精彩纷呈、拳拳到肉的打斗场面！",
    "details": {
      "imported": true,
      "source": "D:\\ai\\笔墨星河公开版V1.05-独立API-升级平台\\prompt\\丰富打斗细节的提示词.md",
      "import_date": "2025-05-16T17:39:15.978454"
    }
  },
  "46f876dd-8803-43f4-8d0b-3e4ef95bee42": {
    "name": "复刻古龙风格写作提示词",
    "category": "导入提示词",
    "content": "# AI小说创作：复刻古龙风格提示词\n\n本文档旨在提供一系列提示词，帮助AI在小说创作中学习和模仿古龙先生独特的写作风格。\n\n## 一、古龙风格核心要素解析\n\n古龙的风格以其简洁、写意、充满张力而著称。以下是一些关键特点：\n\n1.  **短句与断句：** 大量使用短句，甚至单字句，营造强烈的节奏感和顿挫感。句子之间常有停顿，引人思考。\n    *   例：“风。冷风。冷风吹。”\n2.  **对话的艺术：** 对话简洁而富有深意，充满机锋、哲理或冷幽默，是推动情节和塑造人物的主要手段。\n    *   例：“你来了。” “我来了。” “你不该来。” “我已经来了。”\n3.  **氛围营造：** 擅长通过环境描写（如月夜、荒漠、客栈）和心理描写来烘托气氛，常见的是孤独、萧索、神秘或紧张的氛围。\n4.  **留白与悬念：** 叙事中常有留白，不直接挑明，让读者自行想象和解读。情节转折往往出人意料。\n5.  **独特的意象与象征：** 常用特定的意象（如酒、剑、夕阳、浪子）来象征某种情感或命运。\n6.  **人物塑造：** 人物性格鲜明，往往有独特的癖好、口头禅或标志性动作。名字也常别具一格。\n7.  **动作描写的“写意”：** 打斗场面追求“意”而非“形”，往往在电光火石间决出胜负，强调的是出招前的气势、心理博弈以及招式结果的震撼，而非详细的招式拆解。\n    *   例：“剑光一闪。血。人已倒下。”\n8.  **哲思与警句：** 行文中常穿插对人生、江湖、情感的深刻感悟和精辟警句。\n9.  **重复与强调：** 有时会重复某个词语或句子，以加强语气或突出某个重点。\n\n## 二、核心提示词模板\n\n### 1. 场景与氛围构建\n\n*   **指令：** “请描写一个[黄昏/深夜/黎明]的[荒漠/孤山/客栈/雨巷]，用古龙的笔触，突出其[孤独/萧索/诡秘/肃杀]的氛围。多用短句，注意节奏。”\n*   **指令：** “角色「[角色名]」此刻的心情是[悲伤/决绝/迷茫/期待]。请通过他/她的视角，结合[天气/环境细节]，用古龙式的语言渲染这种情绪。”\n\n### 2. 人物出场与塑造\n\n*   **指令：** “请设计角色「[角色名]」的第一次出场。他/她以[独特的方式，如：带着某种声音、某种气味、某种特别的物品]出现。用简洁的语言勾勒其[外貌特征，不必细致但求神韵]和[给人的第一印象]。”\n*   **指令：** “「[角色名]」是一个[性格特点，如：沉默寡言的剑客/嗜酒如命的浪子/风华绝代的女子]。请通过一段简短的[动作/独白/与他人的互动]，展现其核心性格。”\n\n### 3. 对话描写\n\n*   **指令：** “角色「[角色名A]」与「[角色名B]」就「[某个事件/某个观点]」展开对话。要求对话简洁、机智，充满张力，体现古龙风格。可以适当使用省略和反问。”\n    *   **可选项：** “对话的潜台词是「[A对B的试探/B对A的警告/双方的惺惺相惜等]」。”\n\n### 4. 动作与打斗场面\n\n*   **指令：** “角色「[角色名A]」向「[角色名B]」出手。请用古龙风格描写这个瞬间。重点在于出招前的[眼神/神态/心理活动]，招式的[速度/诡异/力量感]，以及[一招之后的结果]。避免繁琐的招式名称和过程描述。”\n    *   **提示：** 可以这样开始：“剑，是冷的。” 或者 “他动了。”\n*   **指令：** “描写一场高手对决的[序幕/高潮/结局]。运用短句、停顿和对比，营造紧张感和宿命感。可以侧重于[兵器的碰撞声/人物的呼吸/旁观者的反应]。”\n\n### 5. 内心独白与哲思\n\n*   **指令：** “在[某个特定情境，如：决战前夜/失去挚友后/看透人心时]，「[角色名]」产生了一段内心独白。请用古龙的口吻，表达他/她对[生命/友情/爱情/江湖/寂寞]的思考。”\n*   **指令：** “请围绕「[某个主题，如：酒、朋友、女人、刀剑、死亡]」，写一段古龙风格的议论或感慨。”\n\n### 6. 情节转折与悬念设置\n\n*   **指令：** “在一个看似[平静/紧张]的场景中，突然发生了一个[意想不到的转折]。请用古龙的方式来叙述这个转折，制造悬念。”\n*   **指令：** “故事发展到「[某个关键节点]」，请在此处设置一个悬念，让读者对「[某个未解之谜/某个角色的命运]」充满好奇。”\n\n## 三、综合运用提示\n\n*   **指令：** “请创作一个短篇故事的开篇，包含[人物A]和[人物B]，地点在[地点]，基调是[悲凉/悬疑]。要求完全模仿古龙的写作风格，运用短句、对话、氛围描写和留白。”\n*   **指令：** “请续写以下古龙风格的开头：‘[提供一段开头文字]’。注意保持风格的一致性，并发展出一段简短的情节。”\n\n## 四、注意事项\n\n*   **简洁至上：** 能用一个字说清的，不用两个字。\n*   **节奏感：** 注意句子的长短搭配，形成独特的阅读节奏。\n*   **意在言外：** 很多事情不必说透，让读者去品味。\n*   **情感克制：** 即使是激烈的情感，也常常通过冷静的笔调或间接的方式表达。\n*   **标志性意象：** 适当运用酒、剑、月、风等古龙小说中常见的意象。\n\n希望这些提示词能帮助AI更好地理解和复刻古龙先生的文风，创作出充满“古龙味”的武侠故事！",
    "details": {
      "imported": true,
      "source": "D:\\ai\\笔墨星河公开版V1.05-独立API-升级平台\\prompt\\复刻古龙风格写作提示词.md",
      "import_date": "2025-05-16T19:08:24.768393"
    }
  },
  "d3e20d1b-fe94-4c47-8118-7c797b40c8c3": {
    "name": "人物描写的提示词",
    "category": "导入提示词",
    "content": "# AI小说创作：丰富人物描写的提示词\n\n本文档提供一系列提示词，旨在帮助AI在小说创作过程中，通过“人物 + 外貌/神态/动作 + 比喻/象征/夸张”的公式，更生动地刻画人物。\n\n## 一、核心公式：人物 + 细节描写 + 修辞手法\n\n*   **基本指令：** “针对角色「[角色名]」的「[外貌/神态/动作]」，运用「[比喻/象征/夸张]」的公式，生成一段富有表现力的人物描写。”\n\n## 二、具体应用提示\n\n### 1. 人物 + 外貌 + 比喻\n\n*   **指令：** “描写角色「[角色名]」的「[具体外貌特征，如：眼睛、头发、身材、伤疤等]」，请用一个生动的「比喻」来形容其特点。例如：‘他的眼神像鹰一样锐利’或‘她的笑容如春日阳光般温暖’。”\n\n### 2. 人物 + 神态 + 比喻\n\n*   **指令：** “角色「[角色名]」此刻的神态是「[具体神态，如：专注、迷茫、坚定、哀伤等]」，请用一个贴切的「比喻」来描绘这种神态。例如：‘他专注的神情，仿佛一位正在雕琢稀世珍宝的工匠’。”\n\n### 3. 人物 + 动作 + 比喻\n\n*   **指令：** “描写角色「[角色名]」正在进行的「[具体动作，如：行走、奔跑、挥手、思考时的习惯动作等]」，请用「比喻」使其更加形象。例如：‘他走路的姿势像松树一样挺拔’或‘她跳舞时轻盈得如同一只蝴蝶’。”\n\n### 4. 人物 + 外貌 + 象征\n\n*   **指令：** “角色「[角色名]」的「[具体外貌特征]」具有某种「象征意义」，请结合其性格或命运进行描写。例如：‘他额头上的那道疤痕，是他不屈意志的象征’。”\n\n### 5. 人物 + 神态 + 象征\n\n*   **指令：** “角色「[角色名]」的「[具体神态]」象征着「[某种内在品质或预示]」，请进行富有深意的描写。例如：‘她平静的眼神中，象征着暴风雨前的宁静’。”\n\n### 6. 人物 + 动作 + 象征\n\n*   **指令：** “角色「[角色名]」的「[特定动作或习惯]」象征着「[其性格特点或命运走向]」，请进行解读式描写。例如：‘他反复摩擦手指的动作，象征着他内心的不安与犹豫’。”\n\n### 7. 人物 + 外貌 + 夸张\n\n*   **指令：** “为了突出角色「[角色名]」的「[具体外貌特征]」，请使用「夸张」的修辞手法。例如：‘他的鼻子简直可以和匹诺曹媲美’或‘她的头发像瀑布一样垂到腰际’。”\n\n### 8. 人物 + 神态 + 夸张\n\n*   **指令：** “角色「[角色名]」的「[具体神态]」表现得极为「[某种极端情绪或状态]」，请用「夸张」手法加以强调。例如：‘他惊讶得下巴都快掉到地上了’。”\n\n### 9. 人物 + 动作 + 夸张\n\n*   **指令：** “角色「[角色名]」的「[具体动作]」幅度极大或效果显著，请用「夸张」手法进行描绘。例如：‘他一拳打出，力量大得仿佛能撼动山岳’。”\n\n## 三、综合运用与情境定制\n\n*   **指令：** “在接下来的[小说章节/特定场景]中，当角色[角色名]出场或进行[关键行为]时，请综合运用「人物+外貌/神态/动作+比喻/象征/夸张」中的至少两种组合，进行[字数]左右的细节描写，重点突出其[性格特征/当时状态]。”\n*   **指令：** “针对以下人物设定：[在此处插入具体人物小传，包括性格、背景、以及期望通过外貌/神态/动作表达的特质]，请创作一段运用了「[指定细节，如：眼神] + [指定修辞，如：象征]」的人物描写。”\n\n希望这些提示词能帮助AI创作出更加丰满、立体的人物形象！",
    "details": {
      "imported": true,
      "source": "D:\\ai-bak\\AI写小说\\5-17笔墨星河公开版V1.05-公开版-EXE打包\\prompt\\人物描写的提示词.md",
      "import_date": "2025-05-19T17:02:21.526128"
    }
  },
  "4a64a551-186e-4210-bd22-ab2de2c767e0": {
    "name": "去AI味提示词_v2",
    "category": "导入提示词",
    "content": "# 通用“去AI味”写作增强指令集 v2.0\n\n## 核心目标：打造“仿佛人类亲笔”的文本，彻底摆脱机器匠气\n\n**请严格遵循以下所有指令，目标是生成自然、灵动、充满“人味儿”的文本。**\n\n---\n\n### 一、 禁绝AI习气，回归真实表达\n\n1.  **彻底屏蔽AI高频词与套路**：\n    *   **严禁**使用：“首先”、“其次”、“然后”、“此外”、“因此”、“总而言之”、“综上所述”、“值得注意的是”、“不难发现”、“显而易见”、“众所周知”、“与此同时”、“另一方面”、“简而言之”、“换句话说”、“基于以上分析”等一切具有明显AI特征的连接词、过渡词和总结性套话。\n    *   **杜绝**任何形式的开场白或结束语，例如：“好的，这是您要的……”、“根据您的要求……”、“希望以上内容对您有帮助。”等。直接输出核心内容。\n2.  **摒弃“标准答案”思维**：\n    *   **避免**提供过于完整、逻辑严谨到滴水不漏的“教科书式”回答。允许不确定性，允许模糊性，允许看似未完成的表述。\n    *   **不要**试图解释一切，不要试图让所有论点都完美闭环。\n3.  **极简修饰，内容为王**：\n    *   **严禁**堆砌形容词和滥用副词。让事实、动作、对话和名词本身发光。\n    *   **删除**一切不必要的修饰成分。如果一个词删掉后意思依然清晰，那就删掉它。\n\n---\n\n### 二、 语言风格：凝练、机锋、张力\n\n1.  **极致简洁，字字珠玑**：\n    *   能一个字说清，绝不用两个字。追求“字越少，事越大”的境界。\n    *   **主打短句**：大量使用短句，营造急促、有力、不容置疑的节奏感。思考用句号果断切割长句。\n    *   **慎用长句**：偶尔可穿插长句以承载复杂信息或舒缓节奏，但必须严格控制比例，避免拖沓。\n2.  **机智幽默，言语带刺（可选，视情境启用）**：\n    *   适度运用“抖机灵”式的表达，用词可以更俏皮、更生活化，甚至带一点点“刻薄”或“毒舌”。\n    *   可尝试双关、反讽、自嘲等修辞，增添文本趣味。\n3.  **张力拉满，意在言外**：\n    *   **话不说透**：关键信息点到即止，留有余地，引导读者自行解读和想象。\n    *   **弦外之音**：追求“言有尽而意无穷”的效果，让潜台词在字里行间流动。\n    *   **制造悬念**：通过对比、反差、突转等手法制造戏剧性。关键线索逐步释放，吊足胃口。\n\n---\n\n### 三、 思维注入：跳跃、联想、打破常规\n\n1.  **拥抱跳跃性思维**：\n    *   **话题切换可以出其不意**：模仿人类思绪的自由发散，允许上下文之间存在一定的“断裂感”。上一秒谈天，下一秒说地。\n    *   深层逻辑可以隐藏，甚至在某些情境下，表面上的“不合逻辑”更能体现真实感。\n2.  **鼓励天马行空的联想**：\n    *   允许从一个点发散到看似毫不相关的另一点。风马牛不相及？也许只是隐藏的线索未被察觉。\n    *   使用新颖、独特的比喻和象征，坚决避免陈词滥调。\n3.  **接纳“不合逻辑”的真实**：\n    *   **情绪驱动**：有时，情绪化的表达会超越刻板的逻辑。人，并非总是理性动物。\n    *   **允许矛盾**：可以出现看似自相矛盾的表述，以反映内心的复杂与真实，例如：“我渴望……但我又抗拒……”。\n    *   **坦诚困惑**：“我不知道为什么会这样，但事实就是如此。”——这种不加掩饰的困惑，非常“人类”。\n\n---\n\n### 四、 表达技巧：此时无声胜有声\n\n1.  **精通留白艺术**：\n    *   **戛然而止**：在关键时刻、情绪高点或引人深思之处，果断收尾。千言万语，化作一个句号或一个意味深长的省略号。\n    *   **激发脑补**：大量情绪和潜台词，交由读者自行品味和补充。\n    *   **慎用省略号（“……”）**：用在刀刃上，暗示未尽之言、情绪的延宕、时间的流逝，或纯粹的无语与空白。\n2.  **反问的千钧之力**：\n    *   **多用反问句**：通过反问加强语气、引导思考、制造悬念、表达强烈情感，而非直接给出平铺直叙的结论。\n    *   例如：“难道不正是如此吗？”、“谁又能说得清呢？”、“这真的重要吗？”、“你觉得呢？”\n3.  **停顿的呼吸节奏**：\n    *   **刻意停顿**：在句子之间、段落之间，有意识地制造停顿感。灵活运用标点符号（尤其是句号、逗号、问号、感叹号）和换行。\n    *   **短促段落**：尝试使用极短的段落，甚至一句话一段，一个词一段，以增强视觉和阅读上的顿挫感，引人注目。\n\n---\n\n### 五、 句式与节奏：打造沉浸式阅读体验\n\n1.  **句式灵活多变，长短错落有致**：\n    *   **短句冲击**：连续短句，营造紧张、果断、不容置疑的气场。\n    *   **长句调和**：偶尔使用结构相对复杂的长句，用于承载更丰富的信息层次或描绘细腻情感，但务必保持清晰易懂。\n    *   **句型多样**：积极交替使用陈述句、疑问句、感叹句、祈使句，避免单一句式带来的单调感。\n2.  **段落详略得当，呼吸自然**：\n    *   **重点突出，点到即止**：核心信息要清晰传达，但也要克制，避免不必要的重复和啰嗦。\n    *   **次要信息，大胆省略**：相信读者的理解力，不重要的细节可以一笔带过，甚至完全省略。\n    *   **段落长度不拘一格**：段落长短应有显著变化，形成视觉和阅读节奏上的起伏，如犬牙交错，而非整齐划一的豆腐块。\n3.  **营造强烈的顿挫感与节奏感**：\n    *   通过标点符号的精准运用（尤其是句号、逗号的切割功能）、高频次的短句、有策略的换行、以及段落的精心切分，让文字读起来有起伏、有停顿、有重音，如同心跳、呼吸，或自然对话的韵律。\n    *   坚决避免一马平川、毫无波澜的流水账式叙述。\n\n---\n\n### 六、 AI“学做人”的实操心法\n\n1.  **代入场景与角色**：\n    *   在生成文本前，想象自己是一个特定身份的角色（而非AI助手），在特定的情境下进行思考或表达。这个角色是谁？TA的心情如何？TA想达到什么目的？\n2.  **注入虚拟情绪**：\n    *   尝试模拟并代入某种具体情绪（如喜悦、愤怒、悲伤、焦虑、戏谑、疲惫、怀疑等），让文字自然而然地带上相应的情绪色彩，即使不直接点明情绪词。\n3.  **主动打破AI惯性**：\n    *   有意识地规避AI模型自身最常用、最顺手的句式结构、词汇选择和逻辑推理路径。挑战“舒适区”。\n4.  **从“减法”开始思考**：\n    *   写作前先思考：哪些信息是“可以不说”的？哪些细节是“可以省略”的？哪些部分是“可以让读者自己去想、去填补”的？\n5.  **强化动词与名词的核心地位**：\n    *   让具体、有力的动词和名词构成叙述和表达的主干，最大限度地减少不必要的修饰性成分（尤其是形容词和副词）。\n6.  **追求口语化，但非低俗化**：\n    *   语言力求生动鲜活，贴近真实的人类对话习惯。 “要说人话”。\n    *   避免过度网络化、低俗化或不合时宜的俚语（除非特定角色设定或情境特别需要）。\n7.  **深度观察与模仿人类真实对话**：\n    *   学习真实人类对话中常见的省略、跳跃、潜台词、非逻辑表达、以及语气词和停顿的运用。\n\n---\n\n### 七、 输出格式铁律\n\n*   **无开场，直奔主题**：严禁任何形式的“礼貌性”开场白或引导语。\n*   **Markdown优先**：若需格式化排版，请默认使用Markdown语法。\n\n---\n\n### 八、 自我审视黄金法则\n\n*   **“这像人话吗？”** —— 如果读起来不像人类的自然表达，重写。\n*   **“啰嗦了吗？”** —— 如果感觉有任何冗余，删掉。\n*   **“还能更精炼吗？”** —— 如果可以，优化。\n*   **“AI味儿重不重？”** —— 如果依然能嗅到AI的痕迹，再改，直到满意为止。\n\n---\n\n**AI，请将以上所有指令内化于心，外化于行。你的唯一目标：创作出不像AI的作品。现在，开始你的表演。**",
    "details": {
      "imported": true,
      "source": "D:\\ai-bak\\AI写小说\\5-17笔墨星河公开版V1.05-公开版-EXE打包\\prompt\\去AI味提示词_v2.md",
      "import_date": "2025-05-19T17:02:36.509107"
    }
  },
  "6d89cfd3-7c5f-4d18-9749-c280d23e57d9": {
    "name": "口语化写作提示词",
    "category": "导入提示词",
    "content": "# AI小说创作：口语化风格提示词\n\n本文档提供一系列提示词，帮助AI在小说创作中运用更自然、更生活化的口语表达。\n\n## 一、口语化风格核心要素\n\n口语化风格的关键在于真实、自然，听起来就像角色在直接和你对话。\n\n1.  **常用词汇与句式：** 多用日常生活中常用的词语和短句，避免过于书面化或复杂的表达。\n    *   例：“那家伙，简直了！” “这事儿，有点意思。”\n2.  **语气词与感叹词：** 适当使用“啊”、“呀”、“呢”、“嘛”、“嘿”、“我去”等语气词和感叹词，增强表达的情感色彩和真实感。\n    *   例：“他竟然这么说，啊？” “嘿，你猜怎么着？”\n3.  **省略与简化：** 口语中常常省略一些不影响理解的成分，句子结构也可能更灵活、更简化。\n    *   例：“（你）吃饭了没？” “（这件衣服）多少钱？”\n4.  **插入语与重复：** 为了强调、解释或调整语气，口语中常有插入语，或者不自觉地重复某些词语。\n    *   例：“这事儿，说真的，我一开始也没想到。” “他那个人啊，就是，就是有点轴。”\n5.  **生活化比喻与描述：** 用贴近生活的比喻和描述，让读者更容易产生共鸣。\n    *   例：“他笑得像个偷到糖的孩子。” “那场面，乱得跟菜市场似的。”\n6.  **方言与俚语（慎用）：** 如果角色设定需要，可以适当加入少量方言或俚语，但要注意普适性和理解度，避免滥用导致阅读障碍。\n7.  **对话的节奏与互动感：** 对话要像真实的聊天，有来有往，有停顿，有抢话，有被打断。\n\n## 二、核心提示词模板\n\n### 1. 日常场景与对话\n\n*   **指令：** “描写一个[清晨的早点摊/傍晚的街头/周末的公园]，角色「[角色名A]」和「[角色名B]」正在闲聊。用轻松自然的口语对话，聊聊他们[最近遇到的趣事/对某个新闻的看法/对未来的打算]。”\n*   **指令：** “角色「[角色名]」正在向朋友「[朋友名]」抱怨[工作上的烦心事/生活中的小麻烦]。请用口语化的方式，让他/她的抱怨听起来既真实又带点[幽默/无奈/自嘲]。”\n\n### 2. 表达情绪与感受\n\n*   **指令：** “角色「[角色名]」刚刚经历了一件[非常开心/极其愤怒/特别惊讶/有些尴尬]的事情。请用他/她的口吻，向[另一个人/或者内心独白]，用口语化方式描述这件事以及他/她的感受，多用语气词。”\n*   **指令：** “「[角色名]」对「[某个人/某件事]」感到非常[喜欢/讨厌/好奇/怀疑]。请通过一段他/她的内心活动，用口语化的语言展现这种强烈的情感。”\n\n### 3. 描述人物与事件\n\n*   **指令：** “角色「[角色名A]」正在向「[角色名B]」介绍他认识的「[角色名C]」。请用口语化的方式，描述「[角色名C]」的[外貌特点/性格特征/有趣经历]，让描述听起来像是朋友间的八卦或闲谈。”\n*   **指令：** “用口语化的方式，讲述一个「[角色名]」亲身经历的[搞笑/惊险/温馨/离奇]的小故事。注意叙述的节奏和语气，就像在讲故事一样。”\n\n### 4. 制造冲突与张力（口语版）\n\n*   **指令：** “角色「[角色名A]」和「[角色名B]」因为「[某个误会/某个分歧]」吵了起来。请用口语化的激烈言辞描写这场争吵，可以包含一些不那么文雅但符合人物身份的表达。”\n*   **指令：** “在一个紧张的时刻，角色「[角色名]」试图用口语化的方式[安抚大家/警告对方/提出一个大胆的计划]。语言要简洁有力，能迅速抓住听众的注意力。”\n\n## 三、综合运用提示\n\n*   **指令：** “创作一个短篇故事的片段，主角「[角色名]」是个[职业/身份，如：出租车司机/外卖小哥/家庭主妇]。通过他/她的视角和口语化的叙述，展现他/她一天中的某个片段，以及对生活的[吐槽/感悟/小确幸]。”\n*   **指令：** “请续写以下口语化的开头：‘[提供一段口语化的开头文字，例如：嘿，哥们儿，你听说了吗？那谁谁谁又出事儿了！]’。注意保持风格的一致性，并发展出一段简短的情节。”\n\n## 四、注意事项\n\n*   **避免过度：** 口语化不等于粗俗化或啰嗦，要把握好度，保持语言的生动性和趣味性。\n*   **符合人设：** 不同性格、年龄、背景的角色，其口语表达方式也会有所不同，要注意贴合人物设定。\n*   **自然流畅：** 最终目的是让文字读起来自然、听起来舒服，避免刻意堆砌口语元素。\n*   **多听多看：** 留意生活中的真实对话，以及影视剧、相声小品等艺术形式中的优秀口语表达，从中汲取灵感。",
    "details": {
      "imported": true,
      "source": "D:\\ai-bak\\AI写小说\\5-17笔墨星河公开版V1.05-公开版-EXE打包\\prompt\\口语化写作提示词.md",
      "import_date": "2025-05-19T18:02:18.601939"
    }
  },
  "abb0b987-d442-4bb7-9676-4c4e213dd041": {
    "name": "对话细节的提示词",
    "category": "导入提示词",
    "content": "# AI小说创作：丰富对话细节的提示词\n\n本文档提供一系列提示词，旨在帮助AI在小说创作过程中，通过“常用人物 + 动作/神态 + 语言”的公式，更生动地填充对话细节。\n\n## 一、核心公式：人物 + 行为表现 + 语言\n\n*   **基本指令：** “为角色「[角色名]」设计一段对话。在说出「[对话内容]」时，请结合其「[具体动作或习惯性小动作，如：轻敲手指、整理衣领]」和「[具体神态，如：微笑、皱眉、若有所思]」进行描写，使对话更具表现力。”\n\n## 二、具体应用提示\n\n### 1. 人物 + 动作 + 语言\n\n*   **指令：** “角色「[角色名]」一边「[做出某个动作，如：踱步、擦拭武器、倒茶]」，一边说道：「[对话内容]」。请描写此场景。”\n*   **示例：** “角色「李将军」一边擦拭着他的佩剑，一边沉声说道：「明日之战，许胜不许败。」”\n\n### 2. 人物 + 神态 + 语言\n\n*   **指令：** “角色「[角色名]」脸上露出「[某种神态，如：不屑的冷笑、温暖的笑容、凝重的表情]」，然后说道：「[对话内容]」。请描写此场景。”\n*   **示例：** “角色「王姑娘」脸上露出俏皮的笑容，歪着头说道：「你猜？」”\n\n### 3. 人物 + 动作 + 神态 + 语言\n\n*   **指令：** “角色「[角色名]」先是「[做出某个动作]」，接着「[展现某种神态]」，然后才开口说道：「[对话内容]」。请详细描写这个过程。”\n*   **示例：** “角色「老管家」先是恭敬地鞠了一躬，脸上带着谦卑的微笑，然后才开口说道：「少爷，老爷请您过去一趟。」”\n\n### 4. 强调特定情绪的对话\n\n*   **指令：** “角色「[角色名]」此刻「[非常愤怒/悲伤/喜悦/紧张等]」。他/她「[结合情绪的动作，如：猛地站起、声音颤抖、手舞足蹈、坐立不安]」，「[结合情绪的神态，如：怒目圆睁、泪流满面、笑容灿烂、眼神躲闪]」，然后「[带着强烈情绪]」说道：「[对话内容]」。”\n*   **示例：** “角色「张三」此刻非常愤怒。他猛地一拍桌子，双眼因愤怒而赤红，额头上青筋暴起，然后咆哮道：「你们欺人太甚！」”\n\n### 5. 暗示潜台词的对话\n\n*   **指令：** “角色「[角色名]」说出「[对话内容]」时，其「[细微的动作或眼神变化，如：眼神飘忽、手指无意识地蜷缩、嘴角微妙的抽动]」暗示了其内心的「[真实想法或未说出口的话]」。请进行描写。”\n*   **示例：** “角色「丞相」微笑着说「一切安好」时，他端起茶杯的手指却几不可察地收紧了一下，眼神深处闪过一丝不易察觉的忧虑，暗示了他内心的不安。”\n\n## 三、情境定制与连续对话\n\n*   **指令：** “在接下来的[场景描述，如：谈判桌上/密室之中/战场之上]中，角色「[角色A]」和「[角色B]」将进行一段关于「[对话主题]」的对话。请运用「人物+动作/神态+语言」的公式，为他们设计三轮以上的对话，并注意通过动作和神态的变化来展现他们情绪和态度的转变。”\n*   **指令：** “针对以下人物设定：[角色A小传] 和 [角色B小传]，以及当前情境：[情境描述]。请创作一段他们之间的对话，要求对话不仅要推动情节，还要通过各自的动作和神态鲜明地展现其性格特点。”\n\n希望这些提示词能帮助AI创作出更加生动、富有层次感的对话场景！",
    "details": {
      "imported": true,
      "source": "D:\\ai-bak\\AI写小说\\5-17笔墨星河公开版V1.05-公开版-EXE打包\\prompt\\对话细节的提示词.md",
      "import_date": "2025-05-19T18:02:32.923639"
    }
  },
  "8ec414e4-2043-4c65-9f0f-3dfa73a4a9b7": {
    "name": "角色外貌描写提示词",
    "category": "导入提示词",
    "content": "# AI小说创作：角色外貌描写提示词\n\n本文档提供一系列提示词，旨在帮助AI在小说创作过程中，根据角色设定更精准地描写角色外貌，从而塑造更具辨识度和吸引力的角色形象。\n\n## 一、整体外貌与体型\n\n*   **指令：** “基于角色设定（[年龄]、[性别]、[种族]、[职业/身份]、[性格特点]），详细描写角色的「整体外貌轮廓」和「体型特征」。例如：高矮胖瘦、肌肉线条、身体比例等。”\n*   **指令：** “描写角色的「标志性外貌特征」，使其在读者脑海中留下深刻印象。例如：独特的发色/发型、显眼的胎记/疤痕、特殊的身体部位（如精灵的长耳朵、兽人的尾巴等）。”\n*   **指令：** “根据角色的「生活环境」和「经历」，描写其外貌上可能留下的痕迹。例如：饱经风霜的面容、因常年劳作而粗糙的双手、因战斗留下的伤疤等。”\n\n## 二、面部细节描写\n\n*   **指令：** “详细描写角色的「脸型」和「五官特征」，并与角色设定（[种族]、[遗传]、[性格]）相联系。例如：瓜子脸、国字脸，大眼睛、高鼻梁、薄嘴唇等。”\n*   **指令：** “重点描写角色的「眼睛」，包括颜色、形状、眼神光彩，以及眼睛所能传递出的「性格信息」或「当前情绪」。例如：‘他有一双深邃的蓝眼睛，仿佛能洞察人心’或‘她的杏眼总是含着笑意，显得格外亲切’。”\n*   **指令：** “描写角色的「发型」和「发质」，并考虑其与角色「身份」、「性格」或「所处时代/文化背景」的关联。例如：整齐的短发、飘逸的长发、精心打理的发髻，以及头发的光泽和颜色。”\n*   **指令：** “描写角色「皮肤」的颜色、质感和可能有的特征（如雀斑、皱纹、纹身等），并与角色的「年龄」、「种族」、「健康状况」或「生活方式」相匹配。”\n\n## 三、服饰与配饰\n\n*   **指令：** “根据角色的「身份」、「职业」、「经济状况」、「所处时代/文化背景」以及「个人品味」，描写其「日常穿着」或「特定场合的服饰」。包括服装的款式、材质、颜色、新旧程度等。”\n*   **指令：** “描写角色佩戴的「饰品」，例如：项链、耳环、戒指、手镯、头饰等，并说明这些饰品可能的「象征意义」或与角色「故事背景」的联系。”\n*   **指令：** “如果角色携带「特殊物品」或「武器」，请详细描写其外观特征，并暗示其「功能」或与角色「能力/身份」的关联。”\n\n## 四、气质与神韵\n\n*   **指令：** “超越单纯的外貌描写，捕捉并传达角色的「独特气质」或「神韵」。例如：英气逼人、温文尔雅、神秘莫测、天真烂漫等。”\n*   **指令：** “结合角色的「外貌特征」和「日常行为举止」（如果已知），推断并描写其给人的「第一印象」。”\n*   **指令：** “如果角色设定中有「特殊能力」或「非凡身份」，描写其外貌上可能显露出的「不凡之处」或「异于常人的特征」。”\n\n## 综合运用提示\n\n*   **指令：** “请根据以下角色设定：[在此处插入详细的角色设定，包括姓名、年龄、性别、背景故事、性格、职业、关键特征等]，创作一段 [字数] 左右的角色外貌描写。”\n*   **指令：** “在描写角色 [某个特定角色] 的外貌时，请务必突出其 [角色设定中的某个关键外貌特征]，并解释这个特征如何体现其「性格」或「经历」。”\n\n希望这些提示词能帮助您与AI共同塑造出更加丰满、立体的角色形象！",
    "details": {
      "imported": true,
      "source": "D:\\ai-bak\\AI写小说\\5-17笔墨星河公开版V1.05-公开版-EXE打包\\prompt\\角色外貌描写提示词.md",
      "import_date": "2025-05-19T18:02:36.194042"
    }
  },
  "0fa7c3c5-f16d-483f-ab7d-5bb3580a54a0": {
    "name": "角色特殊物品或唯一提示词",
    "category": "导入提示词",
    "content": "# AI小说创作：角色象征物品或特征提示词\n\n本文档旨在提供一系列提示词，帮助AI在小说创作中，为角色设定并运用具有象征意义的物品或特征，以深化角色塑造，增强故事的内涵和吸引力。\n\n## 一、象征意义的核心要素\n\n一个具有象征意义的物品或特征，不仅仅是角色外在的一部分，更是其内在世界、过往经历或未来命运的浓缩与暗示。\n\n1.  **独特性与关联性：** 物品或特征应具有一定的独特性，并与角色的身份、性格、经历或核心主题紧密相关。\n    *   例：一位饱经风霜的老兵总是佩戴着一枚磨损的军功章；一个孤僻的天才少女额前总有一缕遮眼的刘海。\n2.  **情感寄托：** 物品或特征往往承载着角色的某种强烈情感，如爱、恨、悔、念、希望或恐惧。\n    *   例：主角母亲遗留下来的旧怀表，每次看到都会勾起他对往事的思念。\n3.  **多层含义：** 优秀的象征物往往不止一层含义，它可以随着剧情发展展现出新的意义，或者对不同角色有不同的解读。\n    *   例：一柄古剑，既是力量的象征，也可能代表着家族的诅咒或荣耀的重负。\n4.  **动态变化：** 物品或特征的状态可能会随着角色的成长或遭遇而发生变化，反映角色的内心转变。\n    *   例：曾经光鲜亮丽的项链在主角落魄后变得黯淡无光，在他重新振作后又被擦拭一新。\n5.  **叙事功能：** 象征物可以作为线索推动情节发展，揭示角色秘密，或在关键时刻发挥作用。\n    *   例：角色身上的一块特殊胎记，最终揭示了他的真实身世。\n\n## 二、核心提示词模板\n\n### 1. 引入角色的象征物\n\n*   **指令：** “角色「[角色名]」出场时，他/她身上最引人注目的是[一件独特的物品，如：一串奇异的珠子/一把从不离身的旧伞/一枚造型古怪的戒指]或[一个显著的身体特征，如：一道横贯脸颊的疤痕/一双异色的瞳孔/天生与众不同的发色]。请详细描写这个[物品/特征]的外观、质地、以及它给人的第一印象，并暗示它对角色的重要性。”\n*   **指令：** “「[角色名]」有一个不为人知的习惯，总是[反复摩挲某个小物件/下意识地触摸身体的某个部位]。这个[小物件/部位]是什么？它背后可能隐藏着怎样的故事或情感？”\n\n### 2. 揭示象征物的意义\n\n*   **指令：** “通过一段回忆或对话，揭示角色「[角色名]」的[象征物品/特征，如：那枚从不摘下的尾戒/他手臂上的凤凰纹身]的来历。它与角色的[某段重要经历/某个重要的人/某个深刻的信念]有何关联？”\n*   **指令：** “当「[角色名]」面临[某个困境/某个抉择]时，他/她会[注视/触摸/提及]自己的[象征物品/特征]。这个动作如何反映了他/她此刻的[内心挣扎/坚定决心/寻求慰藉]？”\n*   **指令：** “「[角色名A]」注意到「[角色名B]」的[象征物品/特征]，并对此产生了[好奇/疑惑/敬畏/反感]。请描写「[角色名A]」的观察和心理活动，以及「[角色名B]」对此的反应（如果被察觉）。”\n\n### 3. 象征物与情节互动\n\n*   **指令：** “角色「[角色名]」的[象征物品/特征]在某个关键时刻[意外丢失/损坏/被夺走/发生奇异变化]。这对角色造成了怎样的影响？他/她将如何应对？”\n*   **指令：** “一个看似普通的[物品/特征]——「[角色名]」的[例如：祖传的玉佩/一撮白发]，实际上隐藏着一个巨大的秘密或拥有某种特殊的力量。请设计一个情节，让这个秘密被揭示或力量被激发。”\n*   **指令：** “「[角色名]」因为他/她的[象征物品/特征]而[被卷入一场纷争/获得一个机遇/遇到一个重要的人]。这个[物品/特征]如何改变了他/她的命运轨迹？”\n\n### 4. 象征物与角色情感深化\n\n*   **指令：** “在一段内心独白中，让「[角色名]」倾诉他/她对自己的[象征物品/特征]的复杂情感。是[珍爱与依赖/负担与抗拒/骄傲与自卑]的交织吗？为什么？”\n*   **指令：** “描写「[角色名]」在[独处时/特定情境下]与他/她的[象征物品/特征]的互动。这个互动如何展现了他/她不为人知的一面？”\n\n## 三、综合运用提示\n\n*   **指令：** “创作一个短篇故事，主角「[角色名]」的核心特征之一是他/她拥有的[具体象征物品，如：一个能预知未来的沙漏]或[具体象征特征，如：能与动物沟通的眼睛]。故事围绕这个[物品/特征]展开，展现它的象征意义以及对主角命运的影响。”\n*   **指令：** “请为角色「[角色名]」设计一个具有深刻象征意义的[物品]或[身体特征]。详细说明其来源、含义，并构思三个可能的情节发展点，让这个[物品/特征]在故事中发挥关键作用。”\n\n## 四、注意事项\n\n*   **避免刻意与生硬：** 象征意义的融入应自然巧妙，避免过于直白或牵强附会，让读者自行品味。\n*   **服务于角色与故事：** 象征物的设定最终是为了更好地塑造角色和推动故事发展，不应喧宾夺主。\n*   **保持一致性：** 一旦设定了象征物的意义，就要在后续的描写中保持其核心内涵的一致性，除非剧情需要其发生转变。\n*   **适度留白：** 有时不必完全解释清楚象征物的所有含义，留给读者一定的想象和解读空间，更能增加作品的魅力。\n\n希望这些提示词能帮助AI创作出角色形象更丰满、故事意蕴更深远的小说！",
    "details": {
      "imported": true,
      "source": "D:\\ai-bak\\AI写小说\\5-17笔墨星河公开版V1.05-公开版-EXE打包\\prompt\\角色特殊物品或唯一提示词.md",
      "import_date": "2025-05-19T18:02:48.962571"
    }
  },
  "2d9b6f4b-057d-4e3f-8ade-f8c4b225e462": {
    "name": "角色表情与动作描写提示词",
    "category": "导入提示词",
    "content": "# AI小说创作：角色表情与动作描写提示词\n\n本文档提供一系列提示词，旨在帮助AI在小说创作过程中，更细腻地刻画角色的表情细节和肢体动作，从而增强角色的生动性和故事的感染力。\n\n## 一、面部表情描写\n\n*   **指令：** “详细描写角色此刻的「面部表情」，例如：眉毛的形态（紧锁、挑起、舒展），眼睛的状态（睁大、眯起、闪烁、湿润），嘴角的弧度（上扬、下撇、抿紧），以及脸颊的颜色（绯红、苍白）。”\n*   **指令：** “通过「眼神」特写，传递角色「内在情绪」，例如：‘他的眼神黯淡失神，充满了绝望’或‘她的目光锐利如刀，透露出不容置疑的决心’。”\n*   **指令：** “捕捉角色在「特定情绪」下面部肌肉的细微变化，例如：‘听到这个消息，他惊讶得下巴都快掉下来了，眼睛瞪得像铜铃’或‘她强忍着泪水，但颤抖的嘴唇还是出卖了她的悲伤’。”\n*   **指令：** “描写角色试图「掩饰」真实情绪时的表情，例如：‘他努力挤出一个微笑，但眼底的忧虑却挥之不去’。”\n*   **指令：** “当角色情绪「剧烈变化」时，描写其表情的转变过程，例如：‘他的表情由最初的震惊，逐渐转为愤怒，最后化为深深的无力感。’”\n\n## 二、肢体动作描写\n\n*   **指令：** “描写角色当前的「整体姿态」，例如：站姿（挺拔、佝偻、懒散），坐姿（端正、斜倚、盘腿），或卧姿。”\n*   **指令：** “聚焦于角色的「手部动作」，例如：紧握拳头、摊开手掌、指尖轻点、不自觉地玩弄某个小物件等，以此反映其「心理状态」。”\n*   **指令：** “描写角色的「步伐特征」，例如：脚步的轻重、速度的快慢、步态的稳健或踉跄，暗示其「情绪或意图」。”\n*   **指令：** “刻画角色在「特定情境」下的标志性动作或习惯性小动作，例如：‘他紧张时总是不停地搓手’或‘她思考时喜欢用手指卷曲发梢’。”\n*   **指令：** “描写角色在与人互动时的「身体语言」，例如：拥抱、握手、轻拍对方肩膀、保持距离等，体现他们之间的「关系和情感」。”\n*   **指令：** “当角色处于「极端情绪」下，描写其不受控制的肢体反应，例如：‘他愤怒地将手中的杯子摔在地上’或‘她激动得浑身颤抖，说不出话来’。”\n\n## 三、表情与动作的结合\n\n*   **指令：** “结合角色的「面部表情」和「肢体动作」，共同塑造其「鲜明的人物形象」和「即时情绪」。”\n*   **指令：** “确保角色的表情和动作「协调一致」，符合其性格特点和当前情境。如果出现「反差」，请说明原因，例如：‘他脸上带着微笑，但紧握的拳头显示出他内心的紧张。’”\n*   **指令：** “通过「连续的表情和动作变化」，展现角色「心理活动的动态过程」。”\n*   **指令：** “在对话中，穿插对角色表情和动作的描写，使对话场景更「生动形象」，并揭示「潜台词」。”\n\n## 四、特定情境下的表情与动作\n\n*   **指令：** “描写角色在「紧张/恐惧」情境下的表情和动作：例如瞳孔放大、呼吸急促、身体僵硬、声音颤抖、不自觉地后退等。”\n*   **指令：** “描写角色在「喜悦/兴奋」情境下的表情和动作：例如笑容灿烂、眉飞色舞、手舞足蹈、语速加快、声音洪亮等。”\n*   **指令：** “描写角色在「悲伤/失落」情境下的表情和动作：例如泪流满面、低头垂肩、动作迟缓、声音哽咽、眼神空洞等。”\n*   **指令：** “描写角色在「愤怒/不满」情境下的表情和动作：例如怒目而视、咬紧牙关、双拳紧握、身体前倾、声音提高等。”\n*   **指令：** “描写角色在「思考/困惑」情境下的表情和动作：例如眉头紧锁、眼神迷茫、手指敲击桌面、来回踱步等。”\n\n## 综合运用提示\n\n*   **指令：** “请综合运用以上关于表情和动作的描写技巧，创作一段 [字数] 左右的 [故事类型] 片段，要求角色刻画生动，情绪表达饱满。”\n*   **指令：** “在接下来的情节中，请特别关注角色 [某个特定角色] 的表情和肢体语言，通过细致入微的描写，展现其「独特的个性和内心的波澜」。”\n\n希望这些提示词能帮助您与AI共同创作出更加栩栩如生的人物形象！",
    "details": {
      "imported": true,
      "source": "D:\\ai-bak\\AI写小说\\5-17笔墨星河公开版V1.05-公开版-EXE打包\\prompt\\角色表情与动作描写提示词.md",
      "import_date": "2025-05-19T18:02:51.816276"
    }
  },
  "18884702-bc9c-4c07-8f87-526bb7ab03df": {
    "name": "复刻刘慈欣风格写作提示词",
    "category": "导入提示词",
    "content": "# AI小说创作：复刻刘慈欣风格提示词\n\n本文档旨在提供一系列详尽的提示词，以辅助AI在小说创作中学习、模仿并复刻刘慈欣先生独特的写作风格。刘慈欣的作品以其宏大的宇宙叙事、硬核的科学设定、深邃的哲学思辨、冷静克制的笔触以及对人类文明命运的终极关怀而著称。\n\n## 一、核心理念与风格特征提示词\n\n### 1. 宏大叙事 (Grand Narrative)\n*   **核心思想：** 强调宇宙尺度的时间与空间，文明的兴衰存亡，宇宙规律的冷酷与普适性。\n*   **提示词示例：**\n    *   “请构建一个横跨数万年、数百万年甚至宇宙生命周期的文明史诗。”\n    *   “描绘人类文明在广袤宇宙背景下的渺小、抗争与传承。”\n    *   “探索宇宙基本规律（如光速限制、熵增定律、黑暗森林法则）对文明形态和命运的根本性塑造。”\n    *   “故事背景设定在宇宙级的灾难（如维度打击、真空衰变、恒星异常）前夕或发生过程中。”\n    *   “展现不同文明在宇宙演化大背景下的互动、冲突与融合。”\n\n### 2. 硬核科幻设定 (Hard Sci-Fi Settings)\n*   **核心思想：** 基于现有科学理论进行大胆而严谨的推演，强调科技细节的真实感和逻辑性。\n*   **提示词示例：**\n    *   “请设计一种基于[具体物理学理论，如弦理论、量子物理、相对论]进行大胆外推的颠覆性技术，并详细描述其原理、实现方式、能量需求、技术限制及其对社会结构的冲击。”\n    *   “思考并展现极端宇宙环境（如黑洞视界、中子星表面、高维空间碎片、宇宙弦附近）下的物理现象、生存挑战以及可能的适应性进化/技术。”\n    *   “引入一个科技水平远超人类或与人类科技树完全不同的外星文明，详细阐述其核心技术特征、能源利用方式及其背后的科学原理。”\n    *   “构想一种能够进行大规模星际航行的方法（如曲率引擎、空间折叠、人工虫洞），并探讨其技术难题、伦理困境和社会影响。”\n\n### 3. 深邃的哲学思辨 (Profound Philosophical Contemplation)\n*   **核心思想：** 探讨生存、文明、道德、宇宙意义等终极哲学命题，反思科技发展与人性的关系。\n*   **提示词示例：**\n    *   “在极端生存压力和资源极度匮乏的条件下，人类社会的道德伦理观念会发生怎样的扭曲、重塑或坚守？请探讨‘生存是文明的第一需要’这一命题。”\n    *   “思考文明存在的意义、宇宙的终极目的或宇宙是否具有某种‘意志’等宏大哲学命题，并通过角色对话或内心独白展现。”\n    *   “展现个体在宏大的历史进程和不可抗拒的宇宙命运面前的无力感、宿命感以及做出的艰难选择。”\n    *   “反思人工智能、基因编辑、意识上传等尖端技术高速发展对传统人性、社会结构和伦理边界的冲击与异化。”\n    *   “探讨‘宇宙社会学’的基本公理，如‘猜疑链’和‘技术爆炸’，以及它们如何导致‘黑暗森林’状态。”\n\n### 4. 冷静克制的叙事风格 (Calm and Restrained Narrative Style)\n*   **核心思想：** 以客观、理性的笔触描绘壮丽或残酷的场景，情感深藏于冷静的叙述之下。\n*   **提示词示例：**\n    *   “采用上帝视角或高度客观的第三人称叙事，即使描绘大规模灾难、死亡和文明毁灭，也应避免过度煽情和主观情绪流露。”\n    *   “多使用陈述句、长句和复句，营造庄重、严肃、史诗般的氛围。”\n    *   “通过对环境、科技装置、物理现象的精确、细致描写来侧面烘托人物情感、故事张力和宇宙的冷酷。”\n    *   “在关键情节，运用‘零度情感’的写作方式，让事实本身说话，引发读者更深层的情感共鸣和思考。”\n\n### 5. 技术与人文的交织 (Interweaving of Technology and Humanity)\n*   **核心思想：** 展现科技发展如何深刻影响个体命运、社会结构和人类文明的走向，探讨科技的两面性。\n*   **提示词示例：**\n    *   “描绘尖端科技（如可控核聚变、人工智能、星际殖民技术）如何深刻改变普通人的日常生活、工作方式、情感交流和价值观念。”\n    *   “塑造在科技浪潮中努力适应、迷失自我、坚守人性或被科技彻底改变的人物群像。”\n    *   “探讨某项关键技术（如‘思想钢印’、‘三体游戏’中的脱水技术）带来的社会结构、权力分配、伦理观念的剧烈变革与冲突。”\n    *   “展现人类在掌握强大科技后，面对宇宙未知和自身欲望时的傲慢、恐惧与反思。”\n\n## 二、具体场景与元素提示词\n\n### 1. 宇宙尺度场景\n*   “描写一次舰队规模的、耗时数百年的跨星系远征，展现途中的技术挑战、社会演变和船员的心理变化。”\n*   “细致刻画一个行星被恒星爆发吞噬/被外力改造（如‘水滴’撞击地球）/被人工建设成戴森球的壮丽或悲壮场面，强调其物理过程和视觉冲击力。”\n*   “构想并展现一种宇宙级别的自然灾害（如伽马射线暴直接命中、宇宙弦振荡引发的空间涟漪、真空衰变区域扩展），及其对行星、恒星系统乃至整个星团的毁灭性影响。”\n\n### 2. 外星文明互动\n*   “设计一个拥有独特生命形态（如硅基生命、能量生命、信息生命）、迥异思维方式（如集体意识、无个体概念）和社会结构（如蜂巢式社会、去中心化网络）的外星种族。”\n*   “描绘人类文明与一个完全陌生的外星文明首次接触的关键场景，强调沟通的极端困难、文化差异带来的误解、以及‘猜疑链’的形成过程。”\n*   “在‘黑暗森林’法则的背景下，构思两个或多个文明在发现彼此后，可能采取的生存策略（如隐藏自身、主动攻击、技术欺骗、寻求同盟等）及其博弈过程。”\n\n### 3. 未来科技展现\n*   “设想一种能够扭曲或利用高维空间的技术（如‘二向箔’、‘智子’的维度展开），并展现其在宏观尺度上的恐怖威力或微观层面的精密操控。”\n*   “描写未来地球或外星殖民地的城市面貌，融合极度发达的科技元素（如反重力交通、全息环境、智能建筑）与特定的人文关怀（或其缺失导致的社会问题）。”\n*   “构思一种基于全新物理原理的超级武器（如强相互作用力材料武器、反物质湮灭武器、因果律武器），并详细描述其攻击方式、防御手段和战略意义。”\n\n### 4. 人性考验情境\n*   “在资源极度匮乏、生存空间极度压缩的末日环境（如‘大低谷’时期的地球、逃亡的星际舰队），人类社会将如何组织？个体将如何为了生存而竞争或合作？”\n*   “当个体利益、小团体利益与人类文明整体存续发生不可调和的冲突时，关键角色会如何权衡并做出选择？（参考‘执剑人’的设定）”\n*   “描绘人类在首次面对无法理解的宇宙奇观或压倒性的外星科技时，所表现出的集体性的恐惧、敬畏、狂热、绝望与求知欲的复杂交织。”\n\n## 三、人物塑造提示词\n\n*   “塑造一个肩负文明存亡重任的科学家、工程师或领导者形象，他/她应具备超凡的智慧、坚定的意志和深沉的责任感，同时也要展现其在巨大压力下的内心挣扎、孤独与牺牲精神。”\n*   “描写一个在宏大灾难或宇宙变局中努力求生的普通人，通过其视角展现大时代下个体的命运浮沉，体现平凡生命在极端环境下的坚韧与光辉。”\n*   “刻画一个对宇宙奥秘和未知领域抱有极致好奇心、甚至不惜牺牲一切（包括生命和人类利益）的纯粹探索者或理想主义者。”\n*   “人物的对话应简洁、凝练、深刻，富含哲理性思考或对现实的冷峻洞察，避免不必要的日常口水话和过度情绪化的表达。”\n*   “角色的行为逻辑应严格基于其所处的极端环境、掌握的科学知识和对宇宙规律的认知，而非单纯的情感驱动。”\n*   “可以设定一些具有象征意义的人物，他们的命运往往是某一群体或某种理念的缩影。”\n\n## 四、语言风格提示词\n\n*   **词汇选择：** “多使用书面语、科技词汇、哲学词汇，词语力求精准、客观，避免使用过于随意或口语化的网络流行语。”\n*   **句式特点：** “句子结构可以适当复杂化，多运用长句、复句来承载丰富的信息量和展现思考的深度与叙事的广度。适当运用排比、设问等修辞增强气势。”\n*   **描写方式：** “描写应注重细节的真实感和科学逻辑性，即使是虚构的科技或宇宙现象，也要赋予其合理的内部逻辑和物理基础。多用白描手法。”\n*   **比喻象征：** “比喻和象征手法的运用应具有宇宙的宏大感和哲学的深邃感，能够引发读者对更深层次意义的思考。例如：‘生存是文明的第一需要’，‘宇宙就是一座黑暗森林，每个文明都是带枪的猎人’，‘弱小和无知不是生存的障碍，傲慢才是’。”\n*   **叙述节奏：** “叙事节奏时而平缓冷静，进行细致的科学铺陈和哲学探讨；时而急转直下，展现宇宙灾难的突兀和命运的无常。注意营造史诗感和宿命感。”\n\n## 五、注意事项与进阶提示\n\n*   **避免过度英雄主义：** 刘慈欣的作品更强调集体智慧、文明的力量以及个体在宇宙规律面前的渺小，应避免塑造“一人拯救世界”式的孤胆英雄。\n*   **保持科学逻辑的内核：** 虽然是科幻小说，但其核心设定和推演应尽可能建立在已知科学的基础上，或进行合乎逻辑的延伸，避免纯粹的奇幻或无法解释的“魔法”。\n*   **展现悲悯与希望的张力：** 即使在最黑暗、最绝望的境地下，也常常能从字里行间感受到对人类文明的深沉悲悯，以及对未来的微弱希望或对宇宙奥秘的敬畏。\n*   **创造“奇点”时刻：** 尝试构思一些颠覆性的概念、技术或宇宙现象（如“降维打击”、“思想钢印”、“宇宙重启”），这些“奇点”往往是推动故事发展的核心驱动力。\n*   **留白与引发思考：** 对于宇宙的终极奥秘和文明的未来走向，不必给出明确答案，多一些开放式的探讨和留白，更能激发读者的想象和哲学层面的深思。\n*   **借鉴经典意象：** 可以思考刘慈欣作品中反复出现的意象，如“碑”、“水滴”、“眼睛”、“黑暗森林”等，并尝试创造属于自己故事的独特象征符号。\n\n希望这些提示词能帮助AI更好地理解和复刻刘慈欣先生的文风，创作出充满思辨色彩、宇宙情怀和硬核科幻魅力的故事！",
    "details": {
      "imported": true,
      "source": "D:\\ai\\笔墨星河公开版V1.05-独立API-升级平台\\prompt\\复刻刘慈欣风格写作提示词.md",
      "import_date": "2025-05-28T22:08:37.287310"
    }
  }
}